UkPostcodeParser-1.1.2.dist-info/DESCRIPTION.rst
UkPostcodeParser-1.1.2.dist-info/METADATA
UkPostcodeParser-1.1.2.dist-info/RECORD
UkPostcodeParser-1.1.2.dist-info/WHEEL
UkPostcodeParser-1.1.2.dist-info/metadata.json
UkPostcodeParser-1.1.2.dist-info/top_level.txt
ukpostcodeparser/__init__.py
ukpostcodeparser/exceptions.py
ukpostcodeparser/parser.py
ukpostcodeparser/test/__init__.py
ukpostcodeparser/test/parser.py
