Metadata-Version: 1.0
Name: UkPostcodeParser
Version: 1.1.2
Summary: UK Postcode parser
Home-page: https://github.com/hamstah/ukpostcodeparser
Author: Simon Brunning
Author-email: simon@brunningonline.net
License: MIT
Platform: UNKNOWN
